MANIFEST.in
README.md
setup.py
pyramid_backend_vgid_oauth2/__init__.py
pyramid_backend_vgid_oauth2.egg-info/PKG-INFO
pyramid_backend_vgid_oauth2.egg-info/SOURCES.txt
pyramid_backend_vgid_oauth2.egg-info/dependency_links.txt
pyramid_backend_vgid_oauth2.egg-info/not-zip-safe
pyramid_backend_vgid_oauth2.egg-info/requires.txt
pyramid_backend_vgid_oauth2.egg-info/top_level.txt
pyramid_backend_vgid_oauth2/adapters/__init__.py
pyramid_backend_vgid_oauth2/adapters/sa.py